mmk_updater/__init__.py
mmk_updater/__main__.py
mmk_updater/generic.py
mmk_updater/i18n/__init__.py
mmk_updater/i18n/data.py
mmk_updater/main.py
mmk_updater/qt/__init__.py
mmk_updater/qt/confirm_dialog.py
mmk_updater/qt/designer/.gitignore
mmk_updater/qt/designer/__init__.py
mmk_updater/qt/designer/update_confirm_dialg.py
mmk_updater/qt/designer/update_confirm_dialg.ui
mmk_updater/qt/main.py
mmk_updater/utils.py
mmk_updater-0.15.6.dist-info/METADATA
mmk_updater-0.15.6.dist-info/WHEEL
mmk_updater-0.15.6.dist-info/licenses/LICENSE
mmk_updater-0.15.6.dist-info/RECORD
