Metadata-Version: 2.4
Name: mmk-updater
Version: 0.15.6
Summary: mmk-updater
License-File: LICENSE
Author: MelianMiko
Author-email: support@mmk.pw
Requires-Python: >=3.10,<4
Classifier: Programming Language :: Python :: 3
Classifier: Programming Language :: Python :: 3.10
Classifier: Programming Language :: Python :: 3.11
Classifier: Programming Language :: Python :: 3.12
Classifier: Programming Language :: Python :: 3.13
Classifier: Programming Language :: Python :: 3.14
Requires-Dist: aiohttp (>=3.10.5)
Requires-Dist: pillow (>=11.0.0)
Requires-Dist: pyqt6 (>=6.7.1)
Requires-Dist: qasync (>=0.27.1)
